NOTICE
onemodel_cli/__init__.py
onemodel_cli/cli.py
onemodel_cli-0.1.0.dist-info/entry_points.txt
onemodel_cli-0.1.0.dist-info/LICENSE
onemodel_cli-0.1.0.dist-info/WHEEL
onemodel_cli-0.1.0.dist-info/METADATA
onemodel_cli-0.1.0.dist-info/RECORD
